<?xml version="1.0" encoding="UTF-8"?>
<!DOCTYPE suite SYSTEM "http://testng.org/testng-1.0.dtd">
<suite name="AutomationTesting">
	<suite-files>
		<suite-file path="automationTesting-Chrome.xml" />
	</suite-files>
	
	<!--  again, the firefox driver is a complete pile of crap. Doesn't work. Tons of reported bugs not being fixed.
	<parameter name="browserType" value="Firefox" />
	<suite-files>
		<suite-file path="automationTesting-Firefox.xml" />
	</suite-files>
	-->
	
	<parameter name="browserType" value="InternetExplorer" />
	<suite-files>
		<suite-file path="automationTesting-IE.xml" />
	</suite-files>
</suite> <!-- Suite -->
